{
  "global_settings": {
    "target_app_id": 570,
    "custom_game_id": "3588570271",
    "server_region": 14,
    "lobby_password": "wuxian",
    "max_players_per_room": 24,
    "seeding_mode": true,
    "debug_mode": true,
    "debug_max_bots_per_room": 23,
    "accounts_per_proxy": 6
  },
  "fleets": [
    {
      "id": "fleet_1",
      "leader": [
        {"username": "XXX","password": "XXX"},
        {"username": "XXX","password": "XXX"}
      ],
      "followers": [
        {"username": "qunrg72307", "password":"hxpzy36381"},
        {"username": "uxxoe82797", "password":"axxmz95559"},
        {"username": "cbxsk86088", "password":"ogbrf16650"},
        {"username": "rewxq18611", "password":"tcajb36675"},
        {"username": "bgsrr13992", "password":"jkmxq98322"},
        {"username": "tyavn97788", "password":"rbrdt37099"},
        {"username": "xrdzq82839", "password":"fnyex27392"},
        {"username": "njekh09591", "password":"wosdg61119"},
        {"username": "hvayx27863", "password":"cmtwp75883"},
        {"username": "qotxf82157", "password":"dgwfu82631"},
        {"username": "dpmgu08269", "password":"rcgsq38025"},
        {"username": "vsbob79985", "password":"cwywd87609"},
        {"username": "qkvvj53379", "password":"eryxg52132"},
        {"username": "bcjkg65973", "password":"rnxbq36850"},
        {"username": "xusna67518", "password":"sbqvc25808"},
        {"username": "aqdra69231", "password":"etgpo77812"},
        {"username": "xkzwd87869", "password":"spzye63720"},
        {"username": "pebbc23258", "password":"jnfsj15782"},
        {"username": "cpfda26623", "password":"jqkbq13069"},
        {"username": "afhez01710", "password":"guzwu30968"},
        {"username": "fejzy66389", "password":"kphub25337"},
        {"username": "vexhf76256", "password":"efghq59305"},
        {"username": "afjmw39616", "password":"prpev17805"},
        {"username": "vddda18793", "password":"svhay79536"},
        {"username": "rndsk82813", "password":"hbvjt02951"},
        {"username": "rpcaa18111", "password":"djeaj52710"},
        {"username": "towwx16589", "password":"xhpat31009"},
        {"username": "ffcpe68529", "password":"ptbge02733"},
        {"username": "ckpwd98880", "password":"tdfyz77513"},
        {"username": "qnjyz60027", "password":"vwfdw08335"},
        {"username": "pqqjp31811", "password":"mfyrj23105"},
        {"username": "tryhh19268", "password":"hwzhq25253"},
        {"username": "cmvqt62606", "password":"focjt62395"},
        {"username": "ubxet68613", "password":"ewyvf53586"},
        {"username": "fdaog30399", "password":"gxbhh31650"},
        {"username": "samsk25039", "password":"armyx65685"},
        {"username": "xdpdr03651", "password":"bhztr83009"},
        {"username": "vbmnu39252", "password":"evfgw58333"},
        {"username": "ktkxh22012", "password":"vmvvu93915"},
        {"username": "ocrqe73757", "password":"duuqp53107"},
        {"username": "dsrsw72700", "password":"ztmmk60677"},
        {"username": "kzfej00563", "password":"oakzd75729"},
        {"username": "svdaq71571", "password":"nrntf32156"},
        {"username": "bybpa01098", "password":"ntzcq63961"},
        {"username": "huedy35913", "password":"aoqyd96682"},
        {"username": "nepmn06183", "password":"tnomr13877"},
        {"username": "budbq91950", "password":"vxjam87897"},
        {"username": "uosvm79331", "password":"gqgvz82122"},
        {"username": "neohn98812", "password":"jkygf60957"},
        {"username": "sjzsx92850", "password":"dctko15188"},
        {"username": "fastn19299", "password":"goguu76687"},
        {"username": "ryuqe21291", "password":"mjaew86088"},
        {"username": "karkp12132", "password":"tdcwv36883"},
        {"username": "knkbh03297", "password":"qobab52378"},
        {"username": "otzue18969", "password":"nnfwu65287"},
        {"username": "zrhog22566", "password":"mbvau67685"},
        {"username": "vnfyp18977", "password":"jcoag77602"},
        {"username": "knhmr72826", "password":"fdest12390"},
        {"username": "xnazn30761", "password":"rruoa23762"},
        {"username": "ztxra63639", "password":"cdqee62711"},
        {"username": "nkydh53331", "password":"seuse59670"},
        {"username": "adbsh05050", "password":"ayqfo80366"},
        {"username": "mhunb31582", "password":"ermtv62202"},
        {"username": "catmo85671", "password":"zomoq23780"},
        {"username": "jneak60881", "password":"axgkf21960"},
        {"username": "amsnd31067", "password":"qdvzp57552"},
        {"username": "gdukq19978", "password":"yrzqr29763"},
        {"username": "ywbuh96615", "password":"gregr27791"},
        {"username": "shatw33039", "password":"foqnv93612"},
        {"username": "pwfre52595", "password":"hodac26295"},
        {"username": "emmab26533", "password":"ohzbb38009"},
        {"username": "nzdej89300", "password":"fhkke62106"},
        {"username": "wbspk08171", "password":"vohkd26596"},
        {"username": "udwrc26018", "password":"zkhvb21279"},
        {"username": "fcmoj17376", "password":"cyodv21771"},
        {"username": "dnpgj20036", "password":"tzwhc68669"},
        {"username": "uguae33695", "password":"eqaqr37587"},
        {"username": "ngmxn13936", "password":"qzxdt88230"},
        {"username": "zfvbb26871", "password":"cvdar00238"},
        {"username": "urbuo31289", "password":"zyvmt57556"},
        {"username": "yjpfq31125", "password":"ynkjh08123"},
        {"username": "scmvs80200", "password":"yzugj55398"},
        {"username": "hctqn37678", "password":"nbwsx95021"},
        {"username": "fqoes56186", "password":"uzxmp19218"},
        {"username": "gjsha36696", "password":"bgaco30002"},
        {"username": "fnjms17121", "password":"gzdde50727"},
        {"username": "zkpvw33590", "password":"synet22062"},
        {"username": "mvybp02190", "password":"bpgup29683"},
        {"username": "rngnc03311", "password":"enozt57623"},
        {"username": "krzvs66605", "password":"gjuzt15715"},
        {"username": "hemmw12586", "password":"jscqc11012"},
        {"username": "otomm51003", "password":"puwcj20036"},
        {"username": "dxzmb72120", "password":"njkrc97067"},
        {"username": "ofhcv67703", "password":"zvpbq06712"},
        {"username": "jgxuo16038", "password":"pbwpj60638"},
        {"username": "axkft07375", "password":"efbmf22357"},
        {"username": "rjjtb99791", "password":"cgawz85352"},
        {"username": "qqofe25125", "password":"pfvkk08602"},
        {"username": "cjozy71791", "password":"zuyny80256"},
        {"username": "wuvzu36537", "password":"mcmwt36665"},
        {"username": "cksgz91366", "password":"vzmrw75380"},
        {"username": "omuwy77656", "password":"qttuw72109"},
        {"username": "qkdwn33608", "password":"qtyab35256"},
        {"username": "xsrwo93999", "password":"kpavy01100"},
        {"username": "canyz06623", "password":"kvxag97670"},
        {"username": "aynon96811", "password":"bsokw73798"},
        {"username": "jonyj95578", "password":"hjqds62031"},
        {"username": "kmxqt36013", "password":"zmkze08118"},
        {"username": "ebtar68910", "password":"qppwd69133"},
        {"username": "yanbv16996", "password":"bwmxm90976"},
        {"username": "mqbef31108", "password":"wnkwz25919"},
        {"username": "emxma18756", "password":"bsycc76396"},
        {"username": "phdhs51787", "password":"ptdgy51618"},
        {"username": "vemkw26020", "password":"crncq28936"},
        {"username": "roknw82790", "password":"umfqh18185"},
        {"username": "wbwqe27185", "password":"cxxry30738"},
        {"username": "ubhju90732", "password":"wnpad01929"},
        {"username": "eqsay99379", "password":"ohqsf29116"},
        {"username": "jotnz00535", "password":"ferba38292"},
        {"username": "nhdef66213", "password":"hjuot70568"},
        {"username": "htfkm67328", "password":"zryqu10987"},
        {"username": "ddxaa61193", "password":"svzmh80921"},
        {"username": "wdzey39177", "password":"cukkg86369"},
        {"username": "cnwym10553", "password":"gczap62669"},
        {"username": "kgccr57368", "password":"dctvh95627"},
        {"username": "fmofk57285", "password":"duvtd17858"},
        {"username": "agjhc05176", "password":"oersj32551"},
        {"username": "annxn98333", "password":"drasv88326"},
        {"username": "yhuob69660", "password":"gqpwr02692"},
        {"username": "fjjbc67190", "password":"eudbj52091"},
        {"username": "bjfdn56873", "password":"shfxq07963"},
        {"username": "vswrv00017", "password":"gndqf12335"},
        {"username": "qjyvu76273", "password":"egzkr70916"},
        {"username": "sjooe20260", "password":"bgukb98935"},
        {"username": "kotvb21929", "password":"jjrxt52610"},
        {"username": "dqkgr90962", "password":"eqktr78290"},
        {"username": "hxjtx96856", "password":"rgjzu83313"},
        {"username": "mgcfj37266", "password":"sysbf71002"},
        {"username": "stkeu16073", "password":"abnhr71083"},
        {"username": "fqedw83662", "password":"yfgmp22278"},
        {"username": "xkcga69627", "password":"vwvyt30287"},
        {"username": "uqopc22632", "password":"zefsz26993"},
        {"username": "zbfeu23803", "password":"mdfns21725"},
        {"username": "bvvbb55167", "password":"txeaz20329"},
        {"username": "qxqcy19538", "password":"gzzyv05129"},
        {"username": "avoyp00716", "password":"nfqgy36852"},
        {"username": "pjyfq36085", "password":"omhqg67738"},
        {"username": "asdjj70852", "password":"znqmk20111"},
        {"username": "gzbrt99006", "password":"ukaqa97925"},
        {"username": "aaqaa78992", "password":"kvwyo12655"},
        {"username": "smehq33133", "password":"ppofq12299"},
        {"username": "kghmt19801", "password":"kzxgk67811"},
        {"username": "twhwk02925", "password":"sphwp81386"},
        {"username": "bjudb66818", "password":"dqjge62278"},
        {"username": "vjjsx16223", "password":"zxqcb38197"},
        {"username": "oycpj00682", "password":"upjhb95150"},
        {"username": "vkcqz08517", "password":"ekxre36917"},
        {"username": "hedhe11677", "password":"qruqs58322"},
        {"username": "hdoyb55057", "password":"usrrp93715"},
        {"username": "svnkx36895", "password":"fxayj52837"},
        {"username": "ftjag97163", "password":"tjtos31968"},
        {"username": "kcvgc00885", "password":"hokbc98291"},
        {"username": "ghwgf01908", "password":"stfde62830"},
        {"username": "wrmjs39931", "password":"dgmtc87672"},
        {"username": "syyye33128", "password":"qxkcv08203"},
        {"username": "zrsue66066", "password":"zeqyk39051"},
        {"username": "dhvft33332", "password":"cyykw73669"},
        {"username": "affzw10136", "password":"mgkwg38257"},
        {"username": "buwev88626", "password":"odboj18717"},
        {"username": "hvmqx73651", "password":"ceooh88223"},
        {"username": "wwjdp29518", "password":"srcmh06693"},
        {"username": "kofux89257", "password":"vhkxa76205"},
        {"username": "tmpyv85505", "password":"jegou77612"},
        {"username": "mqazm26653", "password":"nsqzz13280"},
        {"username": "nzbqz00928", "password":"tkjpp98328"},
        {"username": "xpyjr90689", "password":"sdvve63777"},
        {"username": "unyxe56282", "password":"qzxoe61780"},
        {"username": "zstax50506", "password":"pfukz63836"},
        {"username": "jbxsh19355", "password":"ksrdh95786"},
        {"username": "angnb76812", "password":"gcoqy21827"},
        {"username": "xvyhe70120", "password":"rckhg99675"},
        {"username": "bxdnm37656", "password":"hqcgy05970"},
        {"username": "aeodq02565", "password":"eqgpp59158"},
        {"username": "wwngd53675", "password":"gjjug32788"},
        {"username": "pqura21681", "password":"nkkan63662"},
        {"username": "kwcqr62515", "password":"fwfwt19276"},
        {"username": "pzaza72922", "password":"baxqm00000"},
        {"username": "mujbq76628", "password":"meogt17880"},
        {"username": "dygrc97579", "password":"sbwxb51355"},
        {"username": "drkoe11128", "password":"ntfbg01883"},
        {"username": "jjauf78372", "password":"vxwqm27692"},
        {"username": "kzrne01673", "password":"bkeon68952"},
        {"username": "xmqag73217", "password":"cbnpy12000"},
        {"username": "nqgfy85617", "password":"vaajc90582"},
        {"username": "qsfpe59731", "password":"hsvfv08025"},
        {"username": "nxtnh81802", "password":"ubfez02188"},
        {"username": "baymg83391", "password":"yqruo23517"},
        {"username": "tdrbt06632", "password":"ezmrh88578"},
        {"username": "royeg89305", "password":"ugvpk36589"},
        {"username": "zdczb76080", "password":"fhvqb56881"},
        {"username": "egsaz21860", "password":"zxwqk81021"},
        {"username": "sptpq97093", "password":"onayy51615"},
        {"username": "hmtdm17976", "password":"mzuxa97590"},
        {"username": "kdogn51767", "password":"scozz21733"},
        {"username": "pckvm55575", "password":"gcjqx85666"},
        {"username": "gnrkt87127", "password":"pzncd57099"},
        {"username": "sspbs71701", "password":"qqdgm10880"},
        {"username": "tsybe27818", "password":"eqzja52533"},
        {"username": "tmdgo00896", "password":"sggym12630"},
        {"username": "osjpb87935", "password":"dztbn05828"},
        {"username": "qnfkb78093", "password":"yspbr81588"},
        {"username": "pxdsk62571", "password":"toywk07900"},
        {"username": "cafvu06116", "password":"nhuad93566"},
        {"username": "qsurh72953", "password":"xodxv23100"},
        {"username": "toysh06056", "password":"zjrjw98020"},
        {"username": "moxpw25239", "password":"fnscm20957"},
        {"username": "texjz37101", "password":"zjfqv62892"},
        {"username": "dfsce85013", "password":"wewfx85113"},
        {"username": "vhrua35160", "password":"dyufn69353"},
        {"username": "zkjgd13919", "password":"xxffh32917"},
        {"username": "xaezv27631", "password":"tovug06802"},
        {"username": "anteq72906", "password":"rxasg20831"},
        {"username": "uptyx30089", "password":"kdndf39315"},
        {"username": "tdmta58385", "password":"urxmd12276"},
        {"username": "jctwj06018", "password":"mwqgm69782"},
        {"username": "xumdt62328", "password":"xcqmd80033"},
        {"username": "uzmnu79522", "password":"zoyss88533"},
        {"username": "mazgj13973", "password":"dftqj55191"},
        {"username": "azmyt88795", "password":"qbydw13952"},
        {"username": "csgqq36688", "password":"kcotv35280"},
        {"username": "fvwof59897", "password":"kerdm63610"},
        {"username": "baygv37882", "password":"yqsvg50069"},
        {"username": "rcmgf37792", "password":"gyjoo59917"},
        {"username": "cxmzb89817", "password":"mmfnr25071"},
        {"username": "wgwbc70061", "password":"dzdvy27719"},
        {"username": "aaazv93253", "password":"opnew99330"},
        {"username": "rgngs39132", "password":"ujdwd69125"},
        {"username": "vctka50035", "password":"mpbxc88058"},
        {"username": "jqwoc91715", "password":"ptcvn25258"},
        {"username": "zupcc22899", "password":"bzdcf56589"},
        {"username": "dfema92978", "password":"bjauh12531"},
        {"username": "jjyzf77725", "password":"wegkb77529"},
        {"username": "bkfrt65359", "password":"jsdaz03178"},
        {"username": "bztrg85581", "password":"nxpdz19629"},
        {"username": "ukykm72939", "password":"nrmaj52675"},
        {"username": "rxvff61586", "password":"ccyzg68370"},
        {"username": "hperm03001", "password":"rubnw55911"},
        {"username": "ccxvj21706", "password":"msvnn28153"},
        {"username": "ugavm68179", "password":"rusjd85320"},
        {"username": "emqbs55320", "password":"hukcx10007"},
        {"username": "zhjta27292", "password":"uhoyy82339"},
        {"username": "otdvb39320", "password":"dmqpx85313"},
        {"username": "uwqvm79227", "password":"cdwxj77588"},
        {"username": "ujxnt21650", "password":"rgxyo83600"},
        {"username": "sffak90083", "password":"jthwz96697"},
        {"username": "qmdhq02869", "password":"onfnn85831"},
        {"username": "hpyqk00887", "password":"yjhcm21221"},
        {"username": "jzcwm55099", "password":"tbnun73397"},
        {"username": "mpfso01050", "password":"wzjno88588"},
        {"username": "tejrp00727", "password":"uthhc55637"},
        {"username": "amwma70066", "password":"xygaq08557"},
        {"username": "cybtn56636", "password":"rkqnx36619"},
        {"username": "jumzk19828", "password":"ynbxo12770"},
        {"username": "fpvnz15989", "password":"abscw55896"},
        {"username": "ynupp36362", "password":"hvngr81579"},
        {"username": "tbcss98176", "password":"nfshm50373"},
        {"username": "aqwqn25807", "password":"pkohc75987"},
        {"username": "mubhe21751", "password":"hwgrt67888"},
        {"username": "vkoru65561", "password":"fpoxz36521"},
        {"username": "odpfh39913", "password":"qrybt32229"},
        {"username": "jevkw16950", "password":"ouasm31970"},
        {"username": "gxthr95278", "password":"rtjka78508"},
        {"username": "qpjpc01336", "password":"qcjwo70922"},
        {"username": "odmbt71537", "password":"xbmus29369"},
        {"username": "txrdk57511", "password":"owmho28383"},
        {"username": "tqgby01712", "password":"mxvbs21303"},
        {"username": "ozpyh19736", "password":"kasge77179"},
        {"username": "hzcos72686", "password":"eadav52687"},
        {"username": "fjyyv65132", "password":"ttyaz07958"},
        {"username": "omexf25596", "password":"botzj18505"},
        {"username": "wdqhd81371", "password":"oocgk87910"},
        {"username": "jdhgr97709", "password":"mkpvu72502"},
        {"username": "zydup27008", "password":"ctrvd98706"},
        {"username": "zkuvk87882", "password":"eraxy96206"},
        {"username": "ufjvb50090", "password":"zcxhs56937"},
        {"username": "uakzh93275", "password":"sfaqb55699"},
        {"username": "jqmjc96521", "password":"cvcof82757"},
        {"username": "kyrdt91017", "password":"cvfff72102"},
        {"username": "upbos06032", "password":"amhpj72535"},
        {"username": "ratav35013", "password":"utbyg82513"},
        {"username": "wwzau20810", "password":"jkptw50900"},
        {"username": "mztxu83598", "password":"qvszd96376"},
        {"username": "rjvme36032", "password":"wnrpg55101"},
        {"username": "sfcfy95378", "password":"yzrou09581"},
        {"username": "bxcxy73989", "password":"wxwuj23189"},
        {"username": "wypqs39632", "password":"yquvj99605"},
        {"username": "yfwzd99136", "password":"tgyvp79960"},
        {"username": "jgbky01351", "password":"aufjz65125"},
        {"username": "aareb53821", "password":"bujhq71876"},
        {"username": "pecee80379", "password":"gchhm25079"},
        {"username": "qxpcr71167", "password":"axzuy39002"},
        {"username": "ujaec91293", "password":"nzddu08702"},
        {"username": "vxhxx17115", "password":"kvsjr62050"},
        {"username": "synmn19757", "password":"gfbev83630"},
        {"username": "npafa22369", "password":"gfjdr11921"},
        {"username": "brjox22779", "password":"gwxjv50865"},
        {"username": "wdrxg91659", "password":"fgbho58212"},
        {"username": "zrthc68871", "password":"zsght60787"},
        {"username": "nzech26501", "password":"gzhyo66959"},
        {"username": "ggtge76911", "password":"bvbmd57699"},
        {"username": "ufsqh85068", "password":"frghc93387"},
        {"username": "rnhhu57001", "password":"gybqc07772"},
        {"username": "uqpmj71720", "password":"gajpg78860"},
        {"username": "xyrot95817", "password":"msszd69087"},
        {"username": "fkkjo07568", "password":"foxhw21269"},
        {"username": "foojf29572", "password":"kheha87990"},
        {"username": "zffck97059", "password":"hjuoa86127"},
        {"username": "nomcu96639", "password":"aatej03000"},
        {"username": "kfsxa57537", "password":"xhajc69197"},
        {"username": "ycfpk03716", "password":"xqmhh09299"},
        {"username": "mscve95631", "password":"tfssg61621"},
        {"username": "mvqeo17810", "password":"gvkbd90818"},
        {"username": "vruqq89781", "password":"puatk72009"},
        {"username": "eqzqo68316", "password":"ghrjq53151"},
        {"username": "wqorg20003", "password":"qbjtk63920"},
        {"username": "dpefy69961", "password":"hfobv86657"},
        {"username": "pwnxk65127", "password":"pxhce12121"},
        {"username": "wngwd86507", "password":"sudud55757"},
        {"username": "tdpmf10792", "password":"dhvwf39715"},
        {"username": "wuvuw52928", "password":"ezade61159"},
        {"username": "ghene73385", "password":"gxttr35197"},
        {"username": "chwzt96300", "password":"fgwpr97536"},
        {"username": "rucas71727", "password":"kmort07613"},
        {"username": "dhyeh59938", "password":"okeaf16100"},
        {"username": "hhhbw68558", "password":"rnmbr37503"},
        {"username": "fpjzs82778", "password":"vboaz38878"},
        {"username": "audye06789", "password":"kkafg89755"},
        {"username": "kcdcc23117", "password":"vudeq22822"},
        {"username": "wgakm62107", "password":"ssewa21089"},
        {"username": "tkehg17311", "password":"jhzwn62118"},
        {"username": "vgrgo60971", "password":"vmqpm33329"},
        {"username": "dykog31936", "password":"vyxat85723"},
        {"username": "rrhyk38508", "password":"bxtzr12031"},
        {"username": "qxbau36320", "password":"tbzpn66578"},
        {"username": "swtcs57238", "password":"juwty09091"},
        {"username": "cmebs36323", "password":"tetvx69178"},
        {"username": "fkegh05998", "password":"hodcr21768"},
        {"username": "wppdo11955", "password":"xcejy96136"},
        {"username": "rsfff86735", "password":"cuojd50796"},
        {"username": "cjtcv90603", "password":"cwebd89610"},
        {"username": "ezjqv31822", "password":"dfqcy23898"},
        {"username": "jepkq59195", "password":"hogts07591"},
        {"username": "bukfb38238", "password":"uaoua87161"},
        {"username": "fxfnt68633", "password":"ardro65059"},
        {"username": "ojshp98330", "password":"utzcp85112"},
        {"username": "xyyoa75815", "password":"vrotr76389"},
        {"username": "eqnyw73162", "password":"pxvbz20798"},
        {"username": "yudku55952", "password":"qzsac26906"},
        {"username": "fxrpp37350", "password":"ncdmy65089"},
        {"username": "peptv06935", "password":"azcqy82891"},
        {"username": "jkgpq59261", "password":"jzkup65337"},
        {"username": "rnscw86800", "password":"uxmjx32870"},
        {"username": "mnswv62156", "password":"nbwfs58165"},
        {"username": "ovuof30897", "password":"wxqjn76991"},
        {"username": "hdwor16800", "password":"jqhcg82720"},
        {"username": "xakwp60638", "password":"excmw81971"},
        {"username": "shjjj21130", "password":"vtrdn29683"},
        {"username": "zrpsh25239", "password":"tdxyf21115"},
        {"username": "ntdbv26355", "password":"kmjgv90905"},
        {"username": "zsdab98803", "password":"uspgy50725"},
        {"username": "vjamu97781", "password":"jhckz90520"},
        {"username": "qdxvu21053", "password":"xnzxm15253"},
        {"username": "gatxx33977", "password":"jmdem79681"},
        {"username": "devnr73777", "password":"hupkk19676"},
        {"username": "gcoho17211", "password":"jcwbn05509"},
        {"username": "otymh80688", "password":"ztser70187"},
        {"username": "wkemz99999", "password":"adqnz29980"},
        {"username": "hcguq71200", "password":"keryy02678"},
        {"username": "zfbuf11226", "password":"gbykh51121"},
        {"username": "kqbej73718", "password":"tbjux55571"},
        {"username": "tvyuy58367", "password":"nzysx61673"},
        {"username": "xgtmg18529", "password":"tzuet50758"},
        {"username": "upcyt17320", "password":"uxcav57310"},
        {"username": "fqqqd98751", "password":"fsaxq53119"},
        {"username": "frmkm39375", "password":"fahrf29379"},
        {"username": "jxysr12028", "password":"wvdou28698"},
        {"username": "zbooy68610", "password":"watzc85079"},
        {"username": "yjtht76163", "password":"ysrnh79798"},
        {"username": "rucvs83981", "password":"qywxc98005"},
        {"username": "qdgqy83662", "password":"jhhvm57028"},
        {"username": "yajer38232", "password":"euttt01689"},
        {"username": "kehdo28999", "password":"xdwvu86351"},
        {"username": "bwqvp05260", "password":"fhsvu32850"},
        {"username": "zxhzq88735", "password":"mwgjx93307"},
        {"username": "urngc32503", "password":"kdapd60006"},
        {"username": "texnp33270", "password":"bqxgo22081"},
        {"username": "mkxoe28707", "password":"hvxgg33625"},
        {"username": "kuxyp99173", "password":"jcdur76288"},
        {"username": "pkast28173", "password":"jpdvt53518"},
        {"username": "gcuwd71910", "password":"fecyh58989"},
        {"username": "unogd76331", "password":"sspoh22650"},
        {"username": "hwjym00711", "password":"yxdyc58525"},
        {"username": "mgppk79991", "password":"gpbeg77761"},
        {"username": "ogfga82835", "password":"ykqxf76963"},
        {"username": "ezbft89325", "password":"rdtqq50368"},
        {"username": "agzcx99069", "password":"wfqnq16812"},
        {"username": "upmyw08331", "password":"bfdyb52517"},
        {"username": "eerdc68126", "password":"jctmc61302"},
        {"username": "bbouj91969", "password":"xeguc87878"},
        {"username": "unwdd00591", "password":"otqvz56888"},
        {"username": "vvoyj10967", "password":"wmksk17020"},
        {"username": "kvgrh86021", "password":"mtmrn17266"},
        {"username": "pydpp83067", "password":"qxgpa67657"},
        {"username": "fnuad36696", "password":"benfv99928"},
        {"username": "grvpu07297", "password":"dtmdt20761"},
        {"username": "qqebg32172", "password":"rvyuo71106"},
        {"username": "yorbu05821", "password":"vnwhb68118"},
        {"username": "tycos15757", "password":"vyttb86806"},
        {"username": "tjjgw58169", "password":"cuwga17607"},
        {"username": "oqspz08678", "password":"hkhye02905"},
        {"username": "kjvya00636", "password":"nayfz01153"},
        {"username": "fruup25099", "password":"wyguv89058"},
        {"username": "zmmsx27073", "password":"kyxzu88352"},
        {"username": "etnxa73303", "password":"kqujp69073"},
        {"username": "ouoct22373", "password":"gfjac67791"},
        {"username": "axshh12263", "password":"mvbkw56312"},
        {"username": "cwaqd08716", "password":"evkgs16382"},
        {"username": "vkuec07777", "password":"fjckq02520"},
        {"username": "ecxfd73813", "password":"ypajz93969"},
        {"username": "emrej95228", "password":"xpumt39158"},
        {"username": "xejfm30156", "password":"zhowh63535"},
        {"username": "rwwef78072", "password":"fhrwj72739"},
        {"username": "fwypd30297", "password":"nmqtg19726"},
        {"username": "daghm22735", "password":"xbmhu72588"},
        {"username": "pvvov39135", "password":"xcfmn51938"},
        {"username": "fzyzr08087", "password":"bvust11895"},
        {"username": "hrboa13990", "password":"muxfk66211"},
        {"username": "accsq66218", "password":"xbqhc05809"},
        {"username": "pawnf70673", "password":"dmoqb90103"},
        {"username": "qusyt28612", "password":"doorj76551"},
        {"username": "mxjuj18150", "password":"nfpxe53285"},
        {"username": "wjspu83878", "password":"bvrkk98525"},
        {"username": "brvct15263", "password":"nqznx72399"},
        {"username": "eenqq22361", "password":"njuzs61363"},
        {"username": "dfvuh50167", "password":"mvqeo36951"},
        {"username": "uncpn93133", "password":"vzzkt13389"},
        {"username": "vmjma56805", "password":"krxnz19139"},
        {"username": "hskhj23711", "password":"ctmqp50539"},
        {"username": "fvtpb08576", "password":"exnmd20386"},
        {"username": "vmfro59336", "password":"neszz38521"},
        {"username": "grshh77076", "password":"sdebx53193"},
        {"username": "grapc17758", "password":"adrqp17667"},
        {"username": "fqxnr17763", "password":"yfwxw75256"},
        {"username": "svzdm88189", "password":"boytp57095"},
        {"username": "rpapc62329", "password":"cpmxy93590"},
        {"username": "xgnkh78826", "password":"eobxf79897"},
        {"username": "hzofj87220", "password":"afddz08368"},
        {"username": "sdcht52118", "password":"dmozj68319"},
        {"username": "jjhqe20389", "password":"zejwd88766"},
        {"username": "badsz87997", "password":"ebtyj85551"},
        {"username": "xujtw63615", "password":"myhaa00775"},
        {"username": "fyeax20332", "password":"dasxs50038"},
        {"username": "wyqwy88059", "password":"thddx30808"},
        {"username": "eymjc90507", "password":"tozro16599"},
        {"username": "oywyx12308", "password":"ukzgd15837"},
        {"username": "qmhoy91188", "password":"ownox97756"},
        {"username": "qoyas72007", "password":"hgtvz71268"},
        {"username": "hrsjy93758", "password":"wnvon19328"},
        {"username": "axahw55267", "password":"rfeev25090"},
        {"username": "tgwxg98663", "password":"jkedj93931"},
        {"username": "tjuwg22163", "password":"ojpgb12000"},
        {"username": "ddsww85537", "password":"fmjaa68532"},
        {"username": "zgztg55703", "password":"txvjw66012"},
        {"username": "atufu15778", "password":"ysofp29890"},
        {"username": "kbues88938", "password":"mavyk56281"},
        {"username": "aojkr95628", "password":"efkxg03298"},
        {"username": "cwthn58869", "password":"kamoh19655"},
        {"username": "fdvhr35952", "password":"mtbav28072"},
        {"username": "gnunh06288", "password":"goxqk50315"},
        {"username": "dwegx55985", "password":"qcjov11952"},
        {"username": "muoka32123", "password":"rbsqz76271"},
        {"username": "gqfhq32592", "password":"yfowh60880"},
        {"username": "fgmhc76120", "password":"mtymo66555"},
        {"username": "vxzhy90923", "password":"hzwcr58367"},
        {"username": "fjfku33061", "password":"goceg88850"},
        {"username": "jtodw12837", "password":"yjwow97632"},
        {"username": "urrdp12206", "password":"jkxfx33783"},
        {"username": "vqygc51057", "password":"epmwr82116"},
        {"username": "sqoah21789", "password":"npyqv55682"},
        {"username": "mhjeg87001", "password":"yqkjk58956"},
        {"username": "qxeyy06509", "password":"anxca11355"},
        {"username": "jsunv97907", "password":"wrqwg90375"},
        {"username": "tfvyz78972", "password":"ovvds37585"},
        {"username": "vuguj81371", "password":"ddxzx61767"},
        {"username": "mmnwe75062", "password":"frkpd08967"},
        {"username": "wyouv27931", "password":"dofzt28785"},
        {"username": "stxyn77828", "password":"nbbzh01667"},
        {"username": "xgvzn96310", "password":"podfd26821"},
        {"username": "hzfot02167", "password":"nrary96512"},
        {"username": "ckuxp60996", "password":"vfbzc07735"},
        {"username": "msqvv80128", "password":"krcvk68377"},
        {"username": "qthjw07503", "password":"ftkzd19767"},
        {"username": "ookvw31560", "password":"fvdkd97359"},
        {"username": "udjfc35507", "password":"fspdc20911"},
        {"username": "wdwck68020", "password":"agnum09517"},
        {"username": "abtzj18658", "password":"cwajd00868"},
        {"username": "vdnsz29823", "password":"dzgsj93118"},
        {"username": "rvdhf05303", "password":"gedcg57018"},
        {"username": "aofhd33282", "password":"nqfza20663"},
        {"username": "tmboe72132", "password":"fkjqn23837"},
        {"username": "gvcjz55606", "password":"dnjsv37611"},
        {"username": "nzotu27010", "password":"mdsdv86838"},
        {"username": "bomkq22395", "password":"wnzco06671"},
        {"username": "nfyqo11206", "password":"fnudf93859"},
        {"username": "urajy03688", "password":"qegkt32690"},
        {"username": "xkbfc20788", "password":"dfwnz69093"},
        {"username": "qopgf12838", "password":"nqcmb09851"},
        {"username": "fuckf79073", "password":"wjxtp71325"},
        {"username": "tpnzo90071", "password":"muqbf06925"},
        {"username": "bqhvz70867", "password":"rbjfv99955"},
        {"username": "pfgeb05718", "password":"fmpbe85176"},
        {"username": "dqqbn98531", "password":"wvxvr75295"},
        {"username": "gxbfv96599", "password":"sghwr01725"},
        {"username": "gcjvj56671", "password":"mfqrs56389"},
        {"username": "kojsn76965", "password":"ardct95069"},
        {"username": "ctpuf77138", "password":"pojep66853"},
        {"username": "qwher37883", "password":"hmoyo62656"},
        {"username": "codrb66302", "password":"mqnkd71600"},
        {"username": "qaoqp32631", "password":"crjds10179"},
        {"username": "ugfkb37372", "password":"nramn99927"},
        {"username": "ruarw11056", "password":"qkqrg11273"},
        {"username": "amxfw90561", "password":"dozvn81978"},
        {"username": "vaszc80295", "password":"amxww52898"},
        {"username": "apzrh77383", "password":"abpcp75885"},
        {"username": "pzxqm91558", "password":"tqcfo23997"},
        {"username": "ynqgo23119", "password":"xnpvb86019"},
        {"username": "tsngb52253", "password":"psdmb68660"},
        {"username": "ubraz13577", "password":"hbynb17125"},
        {"username": "xqdxz23010", "password":"veudo79922"},
        {"username": "udhbx78192", "password":"hdcnf30070"},
        {"username": "xyrsz25086", "password":"dfrsx59003"},
        {"username": "cgsoh86601", "password":"aszzk01095"},
        {"username": "kmfhj88297", "password":"hwnge29568"},
        {"username": "ujwsa05261", "password":"khkrp95877"},
        {"username": "dsoav83353", "password":"mhjpu03120"},
        {"username": "nbqbz31737", "password":"ozywa19852"},
        {"username": "bouzw29908", "password":"yyzou91868"},
        {"username": "cuoqb69561", "password":"qkqkp83280"},
        {"username": "pxfsp89925", "password":"bjsha80130"},
        {"username": "ptnju57125", "password":"ujwue60330"},
        {"username": "zmmcy18551", "password":"eamuj93083"},
        {"username": "yavpz32388", "password":"yezbh28695"},
        {"username": "mgyrt97689", "password":"sgcen77162"},
        {"username": "qbxrj20867", "password":"ncayc06570"},
        {"username": "dnupg00258", "password":"zdezn96868"},
        {"username": "pynwc18967", "password":"pqksr10609"},
        {"username": "kavsq82795", "password":"ggqhu85109"},
        {"username": "qaurr66656", "password":"ytskn61255"},
        {"username": "eyjgk23968", "password":"fakan61868"},
        {"username": "apwrq98869", "password":"ccwot00277"},
        {"username": "cgfte00975", "password":"kfvcm65521"},
        {"username": "vsybs21807", "password":"ctamg91790"},
        {"username": "dkbmf19763", "password":"tabtz97726"},
        {"username": "onxhh68081", "password":"utddx20970"},
        {"username": "uzwpg00088", "password":"xsomv98125"},
        {"username": "bnvne73696", "password":"fywnr26327"},
        {"username": "vutfe33069", "password":"ddsxb38927"},
        {"username": "jwfwa39521", "password":"rbyur82626"},
        {"username": "cympm80732", "password":"cxmyc68029"},
        {"username": "atjeb30136", "password":"vojho90893"},
        {"username": "njtjj15068", "password":"vcbaw90282"},
        {"username": "cbmsk57702", "password":"cspeu71032"},
        {"username": "svzco78168", "password":"qjuoz37685"},
        {"username": "pfyvk09726", "password":"pmeev27985"},
        {"username": "xrxyz58733", "password":"padwh79273"},
        {"username": "ahpvf71266", "password":"vskjj50976"},
        {"username": "wtfxh53397", "password":"fkjft96921"},
        {"username": "rqdaj13515", "password":"gsjdy32538"},
        {"username": "tkocf15566", "password":"vorzf56826"},
        {"username": "voduk72325", "password":"mvxfe99627"},
        {"username": "mxesn53722", "password":"gqsuj31255"},
        {"username": "ozaoe82990", "password":"vcoxh23817"},
        {"username": "hxhwt30027", "password":"dopdn39790"},
        {"username": "hfqch80105", "password":"adfzq86593"},
        {"username": "woarb98781", "password":"dvyng70252"},
        {"username": "tspdk68931", "password":"rzsmu35551"},
        {"username": "eqump33502", "password":"vywkt90581"},
        {"username": "enqpu50855", "password":"sqzar70398"},
        {"username": "wrkrh32623", "password":"fejwa97602"},
        {"username": "cjfdp38050", "password":"qsmko87969"},
        {"username": "hpecn66059", "password":"voesw63516"},
        {"username": "tnhue01122", "password":"amoaa73662"},
        {"username": "thoaq85259", "password":"coxzz13882"},
        {"username": "mesfd20836", "password":"afovt69826"},
        {"username": "mgtfy31361", "password":"jdunr75322"},
        {"username": "aswzz33867", "password":"vnasj59978"},
        {"username": "pwxxo58773", "password":"rqdwn87991"},
        {"username": "szekn21232", "password":"akoyt63220"},
        {"username": "beton19209", "password":"bpfja81755"},
        {"username": "oqksk87613", "password":"kmqof78139"},
        {"username": "jugan87908", "password":"vrknn07033"},
        {"username": "fyajj30650", "password":"sqwza88122"},
        {"username": "dkjnn22528", "password":"axwnu36086"},
        {"username": "xxpwj87068", "password":"hwcdm61613"},
        {"username": "ysvwa77653", "password":"orhjq71106"},
        {"username": "anhxg38733", "password":"hyanx63717"},
        {"username": "xqgdc15101", "password":"dwvyr37033"},
        {"username": "zqvnb91123", "password":"qdhdn77980"},
        {"username": "qwsgn99791", "password":"dceta10381"},
        {"username": "burud21350", "password":"qkpjf85879"},
        {"username": "bhbox27506", "password":"rcyuc55087"},
        {"username": "zbfxj82312", "password":"rdjre32138"},
        {"username": "oazso97101", "password":"bdyjw22859"},
        {"username": "wrfjv03997", "password":"soxgm85518"},
        {"username": "qtqtq51691", "password":"dxkqu38973"},
        {"username": "nmxzr28005", "password":"mngha78737"},
        {"username": "doszw90729", "password":"jfcqa68897"},
        {"username": "syqkn33706", "password":"kgzku38312"},
        {"username": "xsgrg97739", "password":"rpsfw63257"},
        {"username": "wwemj95666", "password":"bqknk81396"},
        {"username": "nupbw25056", "password":"ovjkm11901"},
        {"username": "embxp30038", "password":"rsodk30710"},
        {"username": "jjrfz13027", "password":"courh15760"},
        {"username": "bbqgw12075", "password":"exyyt62703"},
        {"username": "hxsuz88658", "password":"vjnhs86298"},
        {"username": "xhcsd80136", "password":"rvxzm79285"},
        {"username": "ccgot52125", "password":"gycfg63299"},
        {"username": "pgrxm55861", "password":"aqgcs75117"},
        {"username": "nrpsn83176", "password":"cdrfz55575"},
        {"username": "rrjhc05695", "password":"eofqb68709"},
        {"username": "hqrww17596", "password":"ancmw63863"},
        {"username": "jvaxa67231", "password":"pcjzs75020"},
        {"username": "tbomt21728", "password":"mkowm10080"},
        {"username": "kyjak76897", "password":"hczcn15907"},
        {"username": "udkyy81363", "password":"ewtqh07832"},
        {"username": "fvyas57989", "password":"rpnuz82866"},
        {"username": "uypza25203", "password":"pcvqr05109"},
        {"username": "fzpzr15901", "password":"omqbu70999"},
        {"username": "dnrrz13573", "password":"sngcu31922"},
        {"username": "pgqyy28589", "password":"sxwco76009"},
        {"username": "vjhnz83100", "password":"kypfk23952"},
        {"username": "gqexv93073", "password":"wnkgz89837"},
        {"username": "hjvfq20200", "password":"wrmvp01860"},
        {"username": "extur78921", "password":"kzyyr22539"},
        {"username": "ttydy05958", "password":"syfjf32803"},
        {"username": "jtooa68555", "password":"dvcvh22285"},
        {"username": "ohzda55902", "password":"pmscw09332"},
        {"username": "bsjaq09115", "password":"vjxek53855"},
        {"username": "tegbf06326", "password":"pbnaw96377"},
        {"username": "qgdsg88685", "password":"pqapc02781"},
        {"username": "tfddc15988", "password":"oeskx89381"},
        {"username": "ptdxo80180", "password":"thfjp69521"},
        {"username": "ksgvb67851", "password":"ycpaf92558"},
        {"username": "xnods55238", "password":"vkjrx91211"},
        {"username": "jjwjh39612", "password":"abcbb95532"},
        {"username": "wfxaw56971", "password":"jzwno85185"},
        {"username": "vahub82006", "password":"fnvea99928"},
        {"username": "aonqs52280", "password":"gzypt67321"},
        {"username": "cwvyz60636", "password":"jyzqs33968"},
        {"username": "wrnbd57993", "password":"qvmkg82853"},
        {"username": "qfuyq11593", "password":"bujrz00137"},
        {"username": "bmkbk13153", "password":"goufy03802"},
        {"username": "ynnyr92802", "password":"dzunx56209"},
        {"username": "kzxug73031", "password":"cabwp30698"},
        {"username": "rpowp76502", "password":"rxhvn00675"},
        {"username": "oueof12585", "password":"ovxsz37000"},
        {"username": "vgwnq11080", "password":"xbakm80609"},
        {"username": "aprjo36605", "password":"prhkn15257"},
        {"username": "ndomh60066", "password":"kffer33656"},
        {"username": "udjhq10603", "password":"omkvt75909"},
        {"username": "fqsbs77176", "password":"cxpuj93536"},
        {"username": "etajg20809", "password":"kvnzj25915"},
        {"username": "tesja62771", "password":"xybkx31369"},
        {"username": "ztozn65102", "password":"okzqm01075"},
        {"username": "hokcf66830", "password":"zfrfh53896"},
        {"username": "xjgnu83699", "password":"vqbgj65575"},
        {"username": "syggy68077", "password":"ypkrp02689"},
        {"username": "nzjcw99082", "password":"jmykp78687"},
        {"username": "eptcc33578", "password":"oqvzw22535"},
        {"username": "zxuqh38118", "password":"oryrk81078"},
        {"username": "gxdes00001", "password":"kqdsa70919"},
        {"username": "kkhvc28912", "password":"cgqrj92867"},
        {"username": "yvrcb99809", "password":"qgxnh30721"},
        {"username": "faarx11711", "password":"qqdep59307"},
        {"username": "hqzxn73017", "password":"efkyg72252"},
        {"username": "euxkv51391", "password":"nsgvj76017"},
        {"username": "gojmm87218", "password":"hdofk30285"},
        {"username": "wcmae02016", "password":"zcfkn89775"},
        {"username": "uwtcc55130", "password":"tcdvc33210"},
        {"username": "tydhn17057", "password":"sbwtw20257"},
        {"username": "fygjc57779", "password":"aygja02071"},
        {"username": "odszq25595", "password":"mugkv06153"},
        {"username": "jvwuz71023", "password":"mmvcx30858"},
        {"username": "fjkur08950", "password":"rdhwp61927"},
        {"username": "wvesj98931", "password":"xeffo30029"},
        {"username": "zncqk50252", "password":"xdpoe99825"},
        {"username": "cpshp91512", "password":"gxvec90683"},
        {"username": "qbzsz56002", "password":"pjwuu62700"},
        {"username": "tzrwg27753", "password":"mkaxg91696"},
        {"username": "xwwmq63931", "password":"bxquc76160"},
        {"username": "pdyaw33660", "password":"dtwgv56099"},
        {"username": "qcudd05727", "password":"dcvan01717"},
        {"username": "nypgm81527", "password":"wnkqe27111"},
        {"username": "jmfde52196", "password":"nerau26709"},
        {"username": "rmxvp29558", "password":"myxsy66108"},
        {"username": "bgsyk19311", "password":"tjzcm82587"},
        {"username": "pbqdg50292", "password":"fdcpg16517"},
        {"username": "qvjgg73661", "password":"wkebo91569"},
        {"username": "ddxtz90117", "password":"ujzwv61069"},
        {"username": "jbxpw50507", "password":"wfjfh65172"},
        {"username": "cztma87582", "password":"yskdo70110"},
        {"username": "puswf32965", "password":"rhxqq03318"},
        {"username": "bscbw88166", "password":"pyadu17039"},
        {"username": "mvppb50617", "password":"roqnc87751"},
        {"username": "cxymx93708", "password":"aphjm78682"},
        {"username": "epmht07892", "password":"pucng68235"},
        {"username": "rtbtn30563", "password":"bbgou79818"},
        {"username": "remhc21998", "password":"pacwn63359"},
        {"username": "azoue32218", "password":"gsuom70615"},
        {"username": "crykp80556", "password":"pargn61858"},
        {"username": "kkajh67569", "password":"gfwho68023"},
        {"username": "osdsx33711", "password":"jnyqc19317"},
        {"username": "twvba29791", "password":"norec57363"},
        {"username": "scppz76389", "password":"pkmyk23831"},
        {"username": "uenut15103", "password":"uzxhv95161"},
        {"username": "cvahg09855", "password":"xhkbz17893"},
        {"username": "xwsvk36315", "password":"dzbww13580"},
        {"username": "bhewu79939", "password":"jequr03692"},
        {"username": "ozrev78370", "password":"jctdy72820"},
        {"username": "tmtcm79682", "password":"vhmzo90166"},
        {"username": "dbnkw69555", "password":"nuszg21222"},
        {"username": "atxpq69097", "password":"hvzkq08517"},
        {"username": "rpgbn85368", "password":"qszzm83650"},
        {"username": "kmnmb18563", "password":"zytje67323"},
        {"username": "mysrj89233", "password":"ttegn76273"},
        {"username": "ddmyt26397", "password":"cyxbf13312"},
        {"username": "fexxv87053", "password":"anndu98176"},
        {"username": "grjuw93033", "password":"bmsgc63653"},
        {"username": "euazs17327", "password":"whgpe13096"},
        {"username": "rjhcc31565", "password":"vwoqg72698"},
        {"username": "rmujd95180", "password":"wqgou21218"},
        {"username": "mkqpn92190", "password":"znwmp96910"},
        {"username": "hsude60581", "password":"nxxxc08589"},
        {"username": "mnjnv18832", "password":"kzaqd01833"},
        {"username": "jqjhs78819", "password":"ptsup53925"},
        {"username": "vfsqg87519", "password":"trxhe61335"},
        {"username": "cajfu11872", "password":"kcjnz68920"},
        {"username": "xgjor13903", "password":"emdeg01172"},
        {"username": "ryoxg71560", "password":"ctxct18829"},
        {"username": "mutpm21801", "password":"rkpao38218"},
        {"username": "nvckj10733", "password":"gnemc01585"},
        {"username": "hugrd93656", "password":"uhzpg79699"},
        {"username": "tgdpw09906", "password":"fbaef15966"},
        {"username": "yeztw92097", "password":"ntjfv59166"},
        {"username": "mffww05793", "password":"cafbx22906"},
        {"username": "ggbyd12359", "password":"hnabn70735"},
        {"username": "qxnyg28922", "password":"pzjnr15073"},
        {"username": "wurky91218", "password":"wytwb16971"},
        {"username": "xmwzm00817", "password":"hqtqh73356"},
        {"username": "xaxeq33388", "password":"zatvc06909"},
        {"username": "czwso16002", "password":"fjvzk06380"},
        {"username": "wukbg12935", "password":"zaaor52281"},
        {"username": "fyopp61101", "password":"cbvaj50581"},
        {"username": "rkfum66708", "password":"wvydy62166"},
        {"username": "yewja11965", "password":"xzqaw97638"},
        {"username": "rzdsv87529", "password":"zfxdg01765"},
        {"username": "uzswm60838", "password":"pvsfz10013"},
        {"username": "aygdn91933", "password":"sptfm88231"},
        {"username": "ztsuj37660", "password":"jmkah19706"},
        {"username": "mqucy88270", "password":"pwxmv10515"},
        {"username": "aqmky19669", "password":"yaqyv62883"},
        {"username": "kjjxb72330", "password":"jvhdq20218"},
        {"username": "rjxmb96063", "password":"zvvag61106"},
        {"username": "answm13051", "password":"yoxpt88592"},
        {"username": "hvrph20039", "password":"yucfr66306"},
        {"username": "szvmf51612", "password":"zwjcw36792"},
        {"username": "cnpbo08902", "password":"acbcy88835"},
        {"username": "dwycx39711", "password":"fquwj99381"},
        {"username": "mexwn98315", "password":"nwhmy37901"},
        {"username": "pdeej63016", "password":"fakzs08938"},
        {"username": "rbgke83179", "password":"xnxcd30228"},
        {"username": "cserb92202", "password":"ymacz67176"},
        {"username": "cwfwm05788", "password":"btpbk19862"},
        {"username": "tecor63589", "password":"srwzf28331"},
        {"username": "qmmuy85556", "password":"bqbkw52210"},
        {"username": "tbgpr55823", "password":"zfqsy07858"},
        {"username": "hmmhj03039", "password":"gxxsj10310"},
        {"username": "ygouz08953", "password":"zdaug96796"},
        {"username": "qxrrc82055", "password":"fojxs03198"},
        {"username": "hqtva75528", "password":"typob75181"},
        {"username": "dorao07706", "password":"odjta52972"},
        {"username": "pmuje91888", "password":"snxxq73955"},
        {"username": "rasqf12895", "password":"fpztd89136"},
        {"username": "cdxcw80673", "password":"xajbt97619"},
        {"username": "kescy02063", "password":"nfjbz25727"},
        {"username": "cppmm56700", "password":"jqoev51210"},
        {"username": "ymkvd69163", "password":"twggd33650"},
        {"username": "owxft13201", "password":"bcdcu37028"},
        {"username": "yktbr23179", "password":"kunss82285"},
        {"username": "skzst20303", "password":"nqvqy53870"},
        {"username": "umodc88785", "password":"obfur87173"},
        {"username": "wuqtn78058", "password":"vejbz01790"},
        {"username": "oyejc05513", "password":"xdrnv18280"},
        {"username": "erexn65952", "password":"ahwfm83526"},
        {"username": "jbmsc15238", "password":"ofufr02566"},
        {"username": "mguzf33967", "password":"zosrc80009"},
        {"username": "ytzat66817", "password":"hrucf39791"},
        {"username": "uqcgc11125", "password":"rfsxv51958"},
        {"username": "sthxh55161", "password":"haabk81265"},
        {"username": "hadhu25308", "password":"szvox61316"},
        {"username": "dfytw30651", "password":"uttwr82008"},
        {"username": "zuhqn29782", "password":"ukbqf60703"},
        {"username": "cynss06851", "password":"ndcqf53500"},
        {"username": "gppyn89627", "password":"yrgvw08086"},
        {"username": "ggxzv39570", "password":"rhfeq03131"},
        {"username": "bpsku83019", "password":"txygn53257"},
        {"username": "zdmpy11380", "password":"sfxcd36221"},
        {"username": "tehyu55517", "password":"yqpuf39776"},
        {"username": "wzuhf11113", "password":"wtysr73822"},
        {"username": "frpng87131", "password":"ofsdd39659"},
        {"username": "nchqb31621", "password":"njhur57200"},
        {"username": "xddjc28210", "password":"rejox77286"},
        {"username": "eqajc79805", "password":"zcdcp62022"},
        {"username": "eoyss06558", "password":"fkcau63993"},
        {"username": "guohe38216", "password":"ptfdu96582"},
        {"username": "kjdab92630", "password":"awqdf57828"},
        {"username": "poxjy96800", "password":"sjycs67710"},
        {"username": "tdowz52000", "password":"tfvgm07890"},
        {"username": "sgsgu92862", "password":"kmowk56000"},
        {"username": "dcjew36127", "password":"swrph59276"},
        {"username": "rygnz20023", "password":"svbrq98929"},
        {"username": "pkmrk85363", "password":"sosfs83938"},
        {"username": "syzgt36050", "password":"sfhjc19305"},
        {"username": "pxejm75939", "password":"hdtfv83633"},
        {"username": "npmmg73213", "password":"sypah02586"},
        {"username": "qktcq55983", "password":"zrkoj70113"},
        {"username": "jhhuc39579", "password":"nxnzz06891"},
        {"username": "jvaxb63709", "password":"yoerz03262"},
        {"username": "xdtkc52368", "password":"khkkp18238"},
        {"username": "psndg31395", "password":"jvwyc01893"},
        {"username": "genwv29813", "password":"wsrwb20919"},
        {"username": "qxabe95138", "password":"unscq17899"},
        {"username": "msfer02701", "password":"zrfpv07371"},
        {"username": "xwzpx82806", "password":"fryax89829"},
        {"username": "rxonj19375", "password":"bfnrg06738"},
        {"username": "fzxrt87281", "password":"jkshg72882"},
        {"username": "onyhy00786", "password":"nfcug37772"},
        {"username": "zzkfv06823", "password":"atcfu72536"},
        {"username": "cswbv06656", "password":"smwcx89591"},
        {"username": "ejtbe80827", "password":"gjxvs93810"},
        {"username": "cjrht22582", "password":"xyxzh80886"},
        {"username": "ctdpb53318", "password":"vbbvv82770"},
        {"username": "auwhe99397", "password":"exnfv02988"},
        {"username": "ruvgp21685", "password":"gotaq70559"},
        {"username": "gbezv01993", "password":"qcrus73968"},
        {"username": "nncod95873", "password":"ynhsk32285"},
        {"username": "khyzd71303", "password":"jckkw82962"},
        {"username": "nvkzo52205", "password":"vxhpd65899"},
        {"username": "adqhj80551", "password":"ucvov52119"},
        {"username": "vstfg17692", "password":"degje38963"},
        {"username": "dadqa33259", "password":"veoxn67163"},
        {"username": "njvqn33725", "password":"qcofd16085"},
        {"username": "wrpzw33150", "password":"cruon87735"},
        {"username": "jxtst21091", "password":"asjce09511"},
        {"username": "wmjzx75376", "password":"oawac26999"},
        {"username": "rgjqy06251", "password":"rhkde96156"},
        {"username": "wjowd90782", "password":"femdx19767"},
        {"username": "czdmq10357", "password":"jhjxq27605"},
        {"username": "uxvxd86068", "password":"yqhsd51182"},
        {"username": "ctpes78912", "password":"zubmw31911"},
        {"username": "stbha96951", "password":"yjfnu35237"},
        {"username": "ctjxd96707", "password":"nerta66261"},
        {"username": "hzweh87221", "password":"xhxdg72253"},
        {"username": "ompur87670", "password":"nbzvv08967"},
        {"username": "pghro37305", "password":"hxgme80708"},
        {"username": "mzgbn17058", "password":"caxzu11519"},
        {"username": "mymya73605", "password":"gmmsv58188"},
        {"username": "xogzu71367", "password":"ywzur83737"},
        {"username": "opwty52215", "password":"ayyav69830"},
        {"username": "fseqq50132", "password":"gbjap23650"},
        {"username": "sqxmo16205", "password":"wfsqk30575"},
        {"username": "buyyv08157", "password":"pxszp53806"},
        {"username": "ntdbw28078", "password":"dvmpx37022"},
        {"username": "jkxrm71228", "password":"bddgf69161"},
        {"username": "dqfcd07291", "password":"otkqz81008"},
        {"username": "evzcm07193", "password":"eombn82379"},
        {"username": "ngbqy65576", "password":"kmsbt21589"},
        {"username": "ejnva81157", "password":"voqxm39828"},
        {"username": "jwbtj23277", "password":"kefry55379"},
        {"username": "tfyno61521", "password":"tkcak58998"},
        {"username": "qkyjo50380", "password":"wduwm15888"},
        {"username": "dexqr05503", "password":"vzudu31099"},
        {"username": "bjgxa58075", "password":"ymaug96581"},
        {"username": "zanwb26690", "password":"thvdc01900"},
        {"username": "csujg28926", "password":"wnkkd83519"},
        {"username": "tvvjj72052", "password":"rkpvy37763"},
        {"username": "pdwuc00912", "password":"afwer62997"},
        {"username": "dbxko89079", "password":"usaqx09798"},
        {"username": "chqqc15829", "password":"unomb81597"},
        {"username": "gqwhb90307", "password":"mxyny36556"},
        {"username": "qepph00937", "password":"tdahg56363"},
        {"username": "qrkxs76987", "password":"hwgpb19167"},
        {"username": "ayxsv90867", "password":"qsytk32658"},
        {"username": "nuhon82125", "password":"yyrfs27716"},
        {"username": "jbddd27889", "password":"rnazn65357"},
        {"username": "goywr03137", "password":"bpzpq52655"},
        {"username": "hvomu38262", "password":"ckmsv29085"},
        {"username": "esxgu78521", "password":"dztxy31821"},
        {"username": "qwvwp53980", "password":"jkusu25868"},
        {"username": "kwyjw26995", "password":"xydtk80736"},
        {"username": "kaxpr58380", "password":"xeyuk30370"},
        {"username": "hzrgw15021", "password":"rsoqp62523"},
        {"username": "ggdxx52232", "password":"xcojd83258"},
        {"username": "eatox90963", "password":"zvmtd99669"},
        {"username": "tmemy93607", "password":"eowqb76590"},
        {"username": "wfjxq23201", "password":"dnujd77607"},
        {"username": "yvxmu65893", "password":"pfrbg56911"},
        {"username": "wrxsv75695", "password":"acrne53936"},
        {"username": "wdjqs66008", "password":"ewspt73281"},
        {"username": "ktxdz72037", "password":"vdhjn79023"},
        {"username": "doqfb11318", "password":"xyrzz82719"},
        {"username": "jvuen30166", "password":"rbpxp85976"},
        {"username": "sbrdo19310", "password":"udopm29933"},
        {"username": "hamuy31086", "password":"vnnya16538"},
        {"username": "snvou51205", "password":"ofcjk00161"},
        {"username": "jycpj62879", "password":"jcyaf23637"},
        {"username": "kcvpp51703", "password":"wesng89885"},
        {"username": "jhudm20852", "password":"dwrhu32237"},
        {"username": "pvvap53205", "password":"akcyr75721"},
        {"username": "fbnoy35018", "password":"dmjxh12828"},
        {"username": "vxtwu25355", "password":"znqdo82155"},
        {"username": "rynvn00233", "password":"ptkak39829"},
        {"username": "jeazf08763", "password":"ferje31531"},
        {"username": "bftue78671", "password":"xvqad50880"},
        {"username": "ttppk21892", "password":"uhnsa60991"},
        {"username": "dxqpm60763", "password":"tjqtg39855"},
        {"username": "qvhrk70532", "password":"tssjg78659"},
        {"username": "yfhez88587", "password":"ghdea75508"},
        {"username": "fehek11266", "password":"wbjgr75183"},
        {"username": "ynruk70916", "password":"vgrfk02023"},
        {"username": "wwmqt26905", "password":"gvoej69976"},
        {"username": "abwhp28557", "password":"gocdg86877"},
        {"username": "mpbwv91668", "password":"qwwbb69689"},
        {"username": "tramh77056", "password":"zxaxo61315"},
        {"username": "auvue62077", "password":"nhgsj33535"},
        {"username": "wrxrj95368", "password":"ctdsj28652"},
        {"username": "rbpgd86372", "password":"frzhq16899"},
        {"username": "rptqx39872", "password":"kzcfa75193"},
        {"username": "yseqs05207", "password":"mpbto53527"},
        {"username": "thqxn85175", "password":"trtzm88601"},
        {"username": "vwkty27300", "password":"repxr06862"},
        {"username": "xhweu06051", "password":"kabrf23068"},
        {"username": "kcojg79860", "password":"xaatt37582"},
        {"username": "kocgs60027", "password":"pnxqq08990"},
        {"username": "mbbnz30833", "password":"anwtv73605"},
        {"username": "vyjjx76657", "password":"gnwyb08753"},
        {"username": "awbyy70068", "password":"bfeaf88969"},
        {"username": "utoca59792", "password":"rykrw97319"},
        {"username": "dyxhx53587", "password":"xcxho68762"},
        {"username": "kpzyf88262", "password":"mgwac68351"},
        {"username": "onuxf98703", "password":"kvarm39373"},
        {"username": "dchnz72557", "password":"xjany97265"},
        {"username": "ahrmv77791", "password":"mknkd81095"},
        {"username": "jfnmm25175", "password":"drmhg63312"},
        {"username": "yukpj73656", "password":"jvvme50178"},
        {"username": "gvtey15293", "password":"yanqt19762"},
        {"username": "ezprh60885", "password":"ebpxf13578"},
        {"username": "gdzwb65226", "password":"pcegs33328"},
        {"username": "wnpnu68611", "password":"amdnr78212"},
        {"username": "uconp75502", "password":"wpydp87397"},
        {"username": "xsqgj72915", "password":"zcsfe91568"},
        {"username": "zsyjr18763", "password":"nzmwn16609"},
        {"username": "qahve21866", "password":"dmenz37530"},
        {"username": "hjjcp56667", "password":"mwejq09711"},
        {"username": "qubmo25588", "password":"syqdd63779"},
        {"username": "uwnfh21019", "password":"wxwef80589"},
        {"username": "fmrqt65186", "password":"bxwcu25303"},
        {"username": "kbfax08112", "password":"qnxnc29232"},
        {"username": "kudvz28966", "password":"tojnu39257"},
        {"username": "nxzjh07698", "password":"orwqc96902"},
        {"username": "zdsem28753", "password":"wnqwd89597"},
        {"username": "pzrrn21201", "password":"ycnoj60217"},
        {"username": "antag59002", "password":"ecrdb93115"},
        {"username": "ptgxx55339", "password":"zwext39813"},
        {"username": "bfrff26167", "password":"zsaau97106"},
        {"username": "aesxa70699", "password":"vbfct01756"},
        {"username": "gtfdr70699", "password":"nfsgt27393"},
        {"username": "erktu99293", "password":"tkezn56389"},
        {"username": "wqvox09613", "password":"ehuxs89369"},
        {"username": "acnsa16586", "password":"kqeyf12993"},
        {"username": "wxtyy83553", "password":"vunfq95893"},
        {"username": "onywr26679", "password":"ywgdq10726"},
        {"username": "ysxvm52936", "password":"cvjny51769"},
        {"username": "azozc53666", "password":"tjvsw99872"},
        {"username": "hjhwx93718", "password":"vanjs67999"},
        {"username": "acnud68563", "password":"tsxfp80929"},
        {"username": "gownd12696", "password":"xnrst98168"},
        {"username": "ssdyg20811", "password":"wbhra90769"},
        {"username": "zxnrb66085", "password":"spkjo12358"},
        {"username": "gorhr39385", "password":"zjanm63683"},
        {"username": "poryo31920", "password":"dtwpm29959"}
     ] 
    } 
  ]
}